itmo_ics_printf/__init__.py
itmo_ics_printf/analyze.py
itmo_ics_printf/errors.py
itmo_ics_printf/events.py
itmo_ics_printf/plotting.py
itmo_ics_printf/py.typed
itmo_ics_printf/tracelog.py
itmo_ics_printf/version.py
itmo_ics_printf-1.0.0.dist-info/METADATA
itmo_ics_printf-1.0.0.dist-info/WHEEL
itmo_ics_printf-1.0.0.dist-info/RECORD
