Metadata-Version: 2.3
Name: itmo-ics-printf
Version: 1.0.0
Summary: Visualisation and analysation tool for 'scanf' - FreeRTOS profiler grabber
Author: Alexander Nalobin
Requires-Python: >=3.11
Classifier: Programming Language :: Python :: 3
Classifier: Programming Language :: Python :: 3.11
Classifier: Programming Language :: Python :: 3.12
Classifier: Programming Language :: Python :: 3.13
Requires-Dist: matplotlib (>=3.7.1,<4.0.0)
